MANIFEST.in
readme.rst
requirements.txt
setup.py
django_location.egg-info/PKG-INFO
django_location.egg-info/SOURCES.txt
django_location.egg-info/dependency_links.txt
django_location.egg-info/requires.txt
django_location.egg-info/top_level.txt
location/__init__.py
location/admin.py
location/models.py
location/runtests.py
location/settings.py
location/signals.py
location/urls.py
location/views.py
location/consumers/__init__.py
location/consumers/foursquare.py
location/consumers/icloud.py
location/consumers/runmeter.py
location/management/__init__.py
location/management/commands/__init__.py
location/management/commands/list_icloud_devices.py
location/management/commands/location_consumer.py
location/migrations/0001_initial.py
location/migrations/0002_auto__add_field_locationsourcetype_ttl_seconds.py
location/migrations/0003_auto__add_locationconsumersettings__del_field_locationsourcetype_ttl_s.py
location/migrations/0004_auto__add_field_locationsource_user.py
location/migrations/0005_move_user_information.py
location/migrations/0006_auto__chg_field_locationsnapshot_user.py
location/migrations/0007_auto__del_field_locationsnapshot_user.py
location/migrations/0008_auto__add_field_locationconsumersettings_icloud_timezone.py
location/migrations/__init__.py
location/static/javascript/._jquery.ui.map.microdata.min.js
location/static/javascript/._jquery.ui.map.microformat.min.js
location/static/javascript/._jquery.ui.map.min.js
location/static/javascript/._jquery.ui.map.overlays.min.js
location/static/javascript/._jquery.ui.map.rdfa.min.js
location/static/javascript/._jquery.ui.map.services.min.js
location/static/javascript/jquery.ui.map.full.min.js
location/static/javascript/jquery.ui.map.microdata.min.js
location/static/javascript/jquery.ui.map.microformat.min.js
location/static/javascript/jquery.ui.map.min.js
location/static/javascript/jquery.ui.map.overlays.min.js
location/static/javascript/jquery.ui.map.rdfa.min.js
location/static/javascript/jquery.ui.map.services.min.js
location/templates/admin/location/app_index.html
location/templates/admin/location/change_list.html
location/templates/admin/location/configure.html
location/templatetags/__init__.py
