Metadata-Version: 1.1
Name: django-location
Version: 2.1.1
Summary: Gather, store, and display real-time location information from Foursquare, iCloud, and more.
Home-page: http://github.com/latestrevision/django-location/
Author: Adam Coddington
Author-email: me@adamcoddington.net
License: UNKNOWN
Platform: UNKNOWN
Classifier: Framework :: Django
Classifier: Intended Audience :: Developers
Classifier: License :: OSI Approved :: MIT License
Classifier: Operating System :: OS Independent
Classifier: Programming Language :: Python
Classifier: Topic :: Scientific/Engineering :: GIS
